djangorestframework_firebase-0.1.2.dist-info/METADATA
djangorestframework_firebase-0.1.2.dist-info/RECORD
djangorestframework_firebase-0.1.2.dist-info/WHEEL
djangorestframework_firebase-0.1.2.dist-info/top_level.txt
rest_framework_firebase/__init__.py
rest_framework_firebase/authentication.py
rest_framework_firebase/settings.py
